<annotation>
	<folder>Picture</folder>
	<filename>c26c18da5ccd-IMG_20170708_102727.jpg</filename>
	<path>C:\Users\14534\Desktop\Capstone Project\Jianmu Deng\Object detection\Picture\c26c18da5ccd-IMG_20170708_102727.jpg</path>
	<source>
		<database>Unknown</database>
	</source>
	<size>
		<width>1368</width>
		<height>1356</height>
		<depth>3</depth>
	</size>
	<segmented>0</segmented>
	<object>
		<name>tongue</name>
		<pose>Unspecified</pose>
		<truncated>0</truncated>
		<difficult>0</difficult>
		<bndbox>
			<xmin>507</xmin>
			<ymin>179</ymin>
			<xmax>911</xmax>
			<ymax>472</ymax>
		</bndbox>
	</object>
</annotation>
